cl_utils/__init__.py
cl_utils/__init__.pyc
cl_utils/ajaxfields.py
cl_utils/backends.py
cl_utils/country.py
cl_utils/data.py
cl_utils/encoding.py
cl_utils/enum.py
cl_utils/forms.py
cl_utils/middleware.py
cl_utils/models.py
cl_utils/prefetching.py
cl_utils/tests.py
cl_utils/thumbs.py
cl_utils/translation_utils.py
cl_utils/utils.py
cl_utils/valuta.py
cl_utils/views.py
cl_utils/widgets.py
cl_utils/decorators/__init__.py
cl_utils/decorators/permissions.py
cl_utils/django_patches/__init__.py
cl_utils/django_patches/patch_mailer.py
cl_utils/django_patches/patch_svglib.py
cl_utils/fields/__init__.py
cl_utils/fields/choice_with_other.py
cl_utils/fields/datetime_fields.py
cl_utils/fields/json_fields.py
cl_utils/fields/readonly.py
cl_utils/inline_edit/__init__.py
cl_utils/inline_edit/urls.py
cl_utils/inline_edit/views.py
cl_utils/inline_edit/templates/inline-edit/inline-edit.js
cl_utils/inline_edit/templatetags/__init__.py
cl_utils/inline_edit/templatetags/inline_edit.py
cl_utils/static/common/advanced_reports/css/jquery.mbox.css
cl_utils/static/common/advanced_reports/css/show-notice.css
cl_utils/static/common/advanced_reports/css/ui.datepicker.css
cl_utils/static/common/advanced_reports/img/calendar.png
cl_utils/static/common/advanced_reports/img/datepicker/ui-bg_flat_0_aaaaaa_40x100.png
cl_utils/static/common/advanced_reports/img/datepicker/ui-bg_flat_55_fbec88_40x100.png
cl_utils/static/common/advanced_reports/img/datepicker/ui-bg_glass_75_d0e5f5_1x400.png
cl_utils/static/common/advanced_reports/img/datepicker/ui-bg_glass_85_dfeffc_1x400.png
cl_utils/static/common/advanced_reports/img/datepicker/ui-bg_glass_95_fef1ec_1x400.png
cl_utils/static/common/advanced_reports/img/datepicker/ui-bg_gloss-wave_55_5c9ccc_500x100.png
cl_utils/static/common/advanced_reports/img/datepicker/ui-bg_inset-hard_100_f5f8f9_1x100.png
cl_utils/static/common/advanced_reports/img/datepicker/ui-bg_inset-hard_100_fcfdfd_1x100.png
cl_utils-1.0.8.dist-info/DESCRIPTION.rst
cl_utils-1.0.8.dist-info/METADATA
cl_utils-1.0.8.dist-info/RECORD
cl_utils-1.0.8.dist-info/WHEEL
cl_utils-1.0.8.dist-info/metadata.json
cl_utils-1.0.8.dist-info/top_level.txt
