Metadata-Version: 2.0
Name: cl-utils
Version: 1.0.8
Summary: A collection of small utilities
Home-page: https://github.com/vikingco/cl_utils
Author: Unleashed NV
Author-email: operations@unleashed.be
License: BSD
Platform: UNKNOWN
Classifier: Intended Audience :: Developers
Classifier: Programming Language :: Python
Classifier: Operating System :: OS Independent
Classifier: Environment :: Web Environment
Classifier: Framework :: Django
